ToolCadeau/__init__.py
ToolCadeau/loaders/__init__.py
ToolCadeau/loaders/engine.py
ToolCadeau/loaders/loader.py
ToolCadeau/preprocessors/__init__.py
ToolCadeau/preprocessors/lang_identifier.py
ToolCadeau/preprocessors/refiner.py
ToolCadeau/summarizers/__init__.py
ToolCadeau/summarizers/bartplm.py
ToolCadeau/summarizers/textrank.py
ToolCadeau-0.1.dist-info/LICENSE.txt
ToolCadeau-0.1.dist-info/METADATA
ToolCadeau-0.1.dist-info/WHEEL
ToolCadeau-0.1.dist-info/top_level.txt
ToolCadeau-0.1.dist-info/RECORD
